[
  {
    "id": "home",
    "title": "Belle Studio by Cristina Lacau",
    "content": "Transformăm frumusețea naturală într-o artă. Cu experiență și pasiune, oferim servicii profesionale de micropigmentare, laminare, make-up, extensii de gene și cursuri acreditate. Descoperă frumusețea la cel mai înalt nivel!",
    "backgroundColor": "#ff7e5f",
    "image": "/images/home.jpg",
    "backgroundImage": "/images/home.jpg"
  },
  {
    "id": "about",
    "title": "Despre Noi",
    "listItems": [
      {
        "title": "Cine suntem?",
        "items": ["Micropigmentare Pro este un concept creat de Belle Studio by Cristina Lacau, care îmbină experiența, creativitatea și tehnologia modernă pentru a oferi servicii de înfrumusețare premium. Fie că ești în căutarea sprâncenelor perfecte, unui look de machiaj profesionist sau dorești să înveți secretele acestei meserii, suntem aici pentru tine."]
      },
      {
        "title": "Misiunea noastră:",
        "items": ["Să oferim clienților noștri servicii de cea mai înaltă calitate, punând accent pe detalii, profesionalism și confort."]
      }
    ],
    "backgroundColor": "#feb47b",
    "image": "/images/about.jpg"
  },
  {
    "id": "services",
    "title": "Servicii",
    "listItems": [
      {
        "title": "Micropigmentare",
        "items": [
          "Sprâncene (tehnici pudrate, fir cu fir, combinate).",
          "Eyeliner semipermanent.",
          "Buze cu efect natural (blush lips)."
        ]
      },
      {
        "title": "Gene și Laminare",
        "items": [
          "Extensii de gene fir cu fir, 2D, 3D.",
          "Laminare sprâncene și gene."
        ]
      },
      {
        "title": "Make-up profesional",
        "items": [
          "Machiaj de zi, de seară, pentru evenimente."
        ]
      },
      {
        "title": "Cursuri acreditate",
        "items": [
          "Micropigmentare sprâncene, eyeliner, buze.",
          "Laminare sprâncene și gene."
        ]
      }
    ],
    "backgroundColor": "#6a11cb",
    "image": "/images/services.jpg"
  },
  {
    "id": "portfolio",
    "title": "Portofoliu",
    "content": "Vezi magia transformărilor noastre! În portofoliul nostru vei găsi imagini înainte și după ale clienților care au avut încredere în serviciile noastre. Fiecare detaliu este realizat cu profesionalism, respectând unicitatea fiecărei persoane.",
    "backgroundColor": "#2575fc",
    "image": "/images/portfolio.jpg"
  },
  {
    "id": "courses",
    "title": "Cursuri",
    "content": "Te invităm să participi la cursurile noastre acreditate, unde vei descoperi secretele unui rezultat impecabil. Oferim suport teoretic și practic, echipamente de ultimă generație și diplomă recunoscută internațional.",
    "listItems": [
      {
        "title": "Ce vei învăța?",
        "items": [
          "Tehnici moderne de micropigmentare.",
          "Proceduri sigure și igienice.",
          "Construirea unui portofoliu profesional."
        ]
      },
      {
        "title": "Beneficii",
        "items": [
          "Ghidare personalizată.",
          "Suport post-curs.",
          "Acces la comunitatea noastră de specialiști."
        ]
      }
    ],
    "backgroundColor": "#1e9600",
    "image": "/images/courses.jpg"
  },
  {
    "id": "contact",
    "title": "Contact",
    "listItems": [
      {
        "title": "Suntem aici pentru tine!",
        "items": [
          "Telefon: 0747 662 436",
          "Locație: Strada Mărăști, nr.4 , Sibiu, Romania",
          "Program: Luni - Vineri: 09:00 - 20:00"
        ]
      }
    ],
    "notes": "Programează-te acum și lasă frumusețea ta să strălucească!",
    "backgroundColor": "#e52d27",
    "image": "/images/contact.jpg"
  }
]
